LRU_tensorflow/LRU_tf.py
LRU_tensorflow/__init__.py
lru_tensorflow-0.1.2.dist-info/licenses/LICENSE.txt
lru_tensorflow-0.1.2.dist-info/METADATA
lru_tensorflow-0.1.2.dist-info/WHEEL
lru_tensorflow-0.1.2.dist-info/top_level.txt
lru_tensorflow-0.1.2.dist-info/RECORD
