Metadata-Version: 2.4
Name: LRU-tensorflow
Version: 0.1.2
Summary: Unofficial TensorFlow implementation of a Linear Recurrent Unit, proposed by Google Deepmind.
Home-page: https://github.com/DemandredEng/Linear-Recurrent-Units-Tensorflow
Download-URL: 
Author: Udit Sharma
Author-email: uditsharma.eng@gmail.com
License: MIT
Keywords: Artificial Intelligence,Deep Learning,Recurrent Neural Networks,Linear Recurrent Unit
Classifier: Development Status :: 3 - Alpha
Classifier: Intended Audience :: Developers
Classifier: Topic :: Scientific/Engineering :: Artificial Intelligence
Classifier: License :: OSI Approved :: MIT License
Classifier: Programming Language :: Python :: 3.7
Classifier: Programming Language :: Python :: 3.8
Classifier: Programming Language :: Python :: 3.9
License-File: LICENSE.txt
Requires-Dist: tensorflow>=2.0
Dynamic: author
Dynamic: author-email
Dynamic: classifier
Dynamic: description
Dynamic: description-content-type
Dynamic: home-page
Dynamic: keywords
Dynamic: license
Dynamic: license-file
Dynamic: requires-dist
Dynamic: summary
